{
  "name": "Thiago Oliveira",
  "photo": "https://avatars.githubusercontent.com/u/172036996?v=4",
  "job": "Estudante de programação",
  "location": "São José dos Pinhais - PR",
  "phone": "(41) 99881-3135",
  "email": "thiago.oliveira_1@hotmail.com",
  "skills": {
    "hardSkills": [
      {
        "name": "Nodejs",
        "logo": "https://raw.githubusercontent.com/thiagolboliveira1/Portfolio/main/data/imgs/js.png"
      },
      {
        "name": "HTML5",
        "logo": "https://raw.githubusercontent.com/thiagolboliveira1/Portfolio/main/data/imgs/html.png"
      },
      {
        "name": "Angular",
        "logo": "https://raw.githubusercontent.com/thiagolboliveira1/Portfolio/main/data/imgs/angular.png"
      },
      {
        "name": "React",
        "logo": "https://raw.githubusercontent.com/thiagolboliveira1/Portfolio/main/data/imgs/react.png"
      },
      {
        "name": "CSS3",
        "logo": "https://raw.githubusercontent.com/thiagolboliveira1/Portfolio/main/data/imgs/css.png"
      },
      {
        "name": "GitHub",
        "logo": "https://raw.githubusercontent.com/thiagolboliveira1/Portfolio/main/data/imgs/github.png"
      },
      {
        "name": "Git",
        "logo": "https://raw.githubusercontent.com/thiagolboliveira1/Portfolio/main/data/imgs/git.png"
      },
      {
        "name": "VsCode",
        "logo": "https://raw.githubusercontent.com/thiagolboliveira1/Portfolio/main/data/imgs/vscode.png"
      }
    ],
    "softSkills": [
      "Liderança",
      "Trabalho em equipe",
      "Flexibilidade",
      "Organização"
    ]
  },
  "languages": [
    "Português BR",
    "Inglês (Básico)"
  ],
  "portfolio": [
    {
      "name": "Criando uma página sobre o Android",
      "url": "https://thiagolboliveira.github.io/projeto-android-2.0/",
      "github": true
    },
    {
      "name": "Criando uma carta pokedex ainda está em construção..",
      "url": "https://thiagolboliveira1.github.io/js-developer-pokedex/",
      "github": true
    },
    {
      "name": "Criando uma página sobre Cordel Moderno por Milton Duarte",
      "url": "https://thiagolboliveira.github.io/projeto-cordel/",
      "github": true
    },
    {
      "name": "Jogo Super Mario",
      "url": "https://thiagolboliveira1.github.io/javascript-voice-recognition/",
      "github": true
    }
  ],
  "professionalExperience": [
    {
      "name": "Sem experiência na área",
      "period": "Não há",
      "description": "Não há"
    }
  ]
}